pddb/__init__.py
pddb/lib/__init__.py
pddb/lib/pddb/__init__.py
pddb/lib/pddb/columns.py
pddb/lib/pddb/pdtbl.py
pddb/lib/pddb/pdvw.py
pddb_genwch-0.0.5.dist-info/LICENSE
pddb_genwch-0.0.5.dist-info/METADATA
pddb_genwch-0.0.5.dist-info/WHEEL
pddb_genwch-0.0.5.dist-info/top_level.txt
pddb_genwch-0.0.5.dist-info/RECORD
