Metadata-Version: 2.1
Name: pddb-genwch
Version: 0.0.5
Summary: Using pandas as db in python
Home-page: https://github.com/genwch/pddb
Author: genwch
Author-email: 
License: UNKNOWN
Platform: UNKNOWN
Classifier: Programming Language :: Python :: 3
Classifier: License :: OSI Approved :: MIT License
Classifier: Operating System :: OS Independent
Requires-Python: >=3.7
Requires-Dist: numpy (==1.20.1)
Requires-Dist: pandas (==1.2.3)
Requires-Dist: pyarrow (==3.0.0)
Requires-Dist: Werkzeug (==1.0.1)
Requires-Dist: pydantic (==1.8.1)
